nose_dehaze/__init__.py
nose_dehaze/constants.py
nose_dehaze/diff.py
nose_dehaze/plugin.py
nose_dehaze/utils.py
nose_dehaze-0.2.0.dist-info/LICENSE
nose_dehaze-0.2.0.dist-info/METADATA
nose_dehaze-0.2.0.dist-info/WHEEL
nose_dehaze-0.2.0.dist-info/entry_points.txt
nose_dehaze-0.2.0.dist-info/top_level.txt
nose_dehaze-0.2.0.dist-info/RECORD
