Metadata-Version: 2.1
Name: nose-dehaze
Version: 0.2.0
Summary: A nosetests plugin to format and colorize test failure output for readability.
Home-page: https://github.com/danieliu/nose-dehaze
Author: Daniel Liu
Author-email: idaniel.liu@gmail.com
License: MIT License
Platform: UNKNOWN
Classifier: Development Status :: 3 - Alpha
Classifier: Intended Audience :: Developers
Classifier: License :: OSI Approved :: MIT License
Classifier: Programming Language :: Python :: 2.7
Classifier: Programming Language :: Python :: 3.6
Classifier: Programming Language :: Python :: 3.7
Classifier: Programming Language :: Python :: 3.8
Classifier: Programming Language :: Python :: 3.9
Classifier: Topic :: Software Development :: Testing
Requires-Python: >=2.7, !=3.0.*, !=3.1.*, !=3.2.*, !=3.3.*, != 3.4.*, !=3.5.*
Requires-Dist: nose
Requires-Dist: six
Requires-Dist: termcolor
